jmu_openconnect/__init__.py
jmu_openconnect/argument_parser.py
jmu_openconnect/auth.py
jmu_openconnect/exceptions.py
jmu_openconnect/main.py
jmu_openconnect-0.4.1.dist-info/LICENSE
jmu_openconnect-0.4.1.dist-info/METADATA
jmu_openconnect-0.4.1.dist-info/WHEEL
jmu_openconnect-0.4.1.dist-info/entry_points.txt
jmu_openconnect-0.4.1.dist-info/RECORD
