Metadata-Version: 2.1
Name: jmu-openconnect
Version: 0.4.1
Summary: Wrapper script around openconnect for JMU VPN authentication on Linux.
Home-page: https://tabulate.tech/
License: MIT
Author: TabulateJarl8
Author-email: tabulatejarl8@gmail.com
Requires-Python: >=3.10,<4.0
Classifier: Development Status :: 7 - Inactive
Classifier: Environment :: Console
Classifier: Intended Audience :: End Users/Desktop
Classifier: License :: OSI Approved :: MIT License
Classifier: Natural Language :: English
Classifier: Operating System :: POSIX :: Linux
Classifier: Programming Language :: Python :: 3
Classifier: Programming Language :: Python :: 3.10
Classifier: Programming Language :: Python :: 3.11
Classifier: Programming Language :: Python :: 3.12
Classifier: Typing :: Typed
Requires-Dist: selenium (>=4.23.1,<5.0.0)
Requires-Dist: typing-extensions (>=4.12.2,<5.0.0)
Project-URL: Repository, https://github.com/TabulateJarl8/jmu-openconnect
